{
  "Afstemningsområde": "Bække",
  "AfstemningsområdeDagiId": "701386",
  "AfstemningsområdeNummer": 19,
  "FrigivelsesTidspunktUTC": "24-03-2026 15:00:59",
  "Kommune": "Vejen",
  "Kommunekode": 575,
  "Valgart": "Folketingsvalg",
  "Valgdag": "24-03-2026",
  "Valgdeltagelse": [
    {
      "AfgivneStemmer": 138,
      "AntalStemmeberretigedeVælgere": 1402,
      "Tidspunkt": "09:12:00"
    },
    {
      "AfgivneStemmer": 183,
      "AntalStemmeberretigedeVælgere": 1402,
      "Tidspunkt": "10:00:00"
    },
    {
      "AfgivneStemmer": 265,
      "AntalStemmeberretigedeVælgere": 1402,
      "Tidspunkt": "11:00:00"
    },
    {
      "AfgivneStemmer": 342,
      "AntalStemmeberretigedeVælgere": 1402,
      "Tidspunkt": "12:00:00"
    },
    {
      "AfgivneStemmer": 385,
      "AntalStemmeberretigedeVælgere": 1402,
      "Tidspunkt": "13:00:00"
    },
    {
      "AfgivneStemmer": 453,
      "AntalStemmeberretigedeVælgere": 1402,
      "Tidspunkt": "14:00:00"
    },
    {
      "AfgivneStemmer": 528,
      "AntalStemmeberretigedeVælgere": 1402,
      "Tidspunkt": "15:00:00"
    },
    {
      "AfgivneStemmer": 640,
      "AntalStemmeberretigedeVælgere": 1402,
      "Tidspunkt": "16:00:00"
    }
  ]
}
