{
  "Afstemningsområde": "Himmelev",
  "AfstemningsområdeDagiId": "702794",
  "AfstemningsområdeNummer": 6,
  "FrigivelsesTidspunktUTC": "24-03-2026 16:01:21",
  "Kommune": "Roskilde",
  "Kommunekode": 265,
  "Valgart": "Folketingsvalg",
  "Valgdag": "24-03-2026",
  "Valgdeltagelse": [
    {
      "AfgivneStemmer": 1427,
      "AntalStemmeberretigedeVælgere": 5986,
      "Tidspunkt": "09:00:00"
    },
    {
      "AfgivneStemmer": 2217,
      "AntalStemmeberretigedeVælgere": 5986,
      "Tidspunkt": "11:01:00"
    },
    {
      "AfgivneStemmer": 2842,
      "AntalStemmeberretigedeVælgere": 5986,
      "Tidspunkt": "13:00:00"
    },
    {
      "AfgivneStemmer": 3465,
      "AntalStemmeberretigedeVælgere": 5986,
      "Tidspunkt": "15:00:00"
    },
    {
      "AfgivneStemmer": 4348,
      "AntalStemmeberretigedeVælgere": 5986,
      "Tidspunkt": "17:00:00"
    }
  ]
}
