{
  "Afstemningsområde": "Stengård",
  "AfstemningsområdeDagiId": "700934",
  "AfstemningsområdeNummer": 6,
  "FrigivelsesTidspunktUTC": "24-03-2026 15:06:47",
  "Kommune": "Gladsaxe",
  "Kommunekode": 159,
  "Valgart": "Folketingsvalg",
  "Valgdag": "24-03-2026",
  "Valgdeltagelse": [
    {
      "AfgivneStemmer": 2194,
      "AntalStemmeberretigedeVælgere": 6054,
      "Tidspunkt": "12:00:00"
    },
    {
      "AfgivneStemmer": 3535,
      "AntalStemmeberretigedeVælgere": 6054,
      "Tidspunkt": "16:00:00"
    }
  ]
}
