{
  "Afstemningsområde": "Jægerspris",
  "AfstemningsområdeDagiId": "704070",
  "AfstemningsområdeNummer": 5,
  "FrigivelsesTidspunktUTC": "24-03-2026 19:04:15",
  "Kommune": "Frederikssund",
  "Kommunekode": 250,
  "Valgart": "Folketingsvalg",
  "Valgdag": "24-03-2026",
  "Valgdeltagelse": [
    {
      "AfgivneStemmer": 1576,
      "AntalStemmeberretigedeVælgere": 6840,
      "Tidspunkt": "10:00:00"
    },
    {
      "AfgivneStemmer": 2448,
      "AntalStemmeberretigedeVælgere": 6840,
      "Tidspunkt": "12:00:00"
    },
    {
      "AfgivneStemmer": 3173,
      "AntalStemmeberretigedeVælgere": 6840,
      "Tidspunkt": "14:00:00"
    },
    {
      "AfgivneStemmer": 3968,
      "AntalStemmeberretigedeVælgere": 6840,
      "Tidspunkt": "16:00:00"
    },
    {
      "AfgivneStemmer": 5051,
      "AntalStemmeberretigedeVælgere": 6840,
      "Tidspunkt": "18:00:00"
    },
    {
      "AfgivneStemmer": 5704,
      "AntalStemmeberretigedeVælgere": 6840,
      "Tidspunkt": "20:00:00"
    }
  ]
}
