{
  "Afstemningsområde": "Nørrevangsskolen",
  "AfstemningsområdeDagiId": "710322",
  "AfstemningsområdeNummer": 27,
  "FrigivelsesTidspunktUTC": "24-03-2026 19:07:31",
  "Kommune": "Randers",
  "Kommunekode": 730,
  "Valgart": "Folketingsvalg",
  "Valgdag": "24-03-2026",
  "Valgdeltagelse": [
    {
      "AfgivneStemmer": 413,
      "AntalStemmeberretigedeVælgere": 3785,
      "Tidspunkt": "09:00:00"
    },
    {
      "AfgivneStemmer": 613,
      "AntalStemmeberretigedeVælgere": 3785,
      "Tidspunkt": "10:00:00"
    },
    {
      "AfgivneStemmer": 835,
      "AntalStemmeberretigedeVælgere": 3785,
      "Tidspunkt": "11:00:00"
    },
    {
      "AfgivneStemmer": 1043,
      "AntalStemmeberretigedeVælgere": 3785,
      "Tidspunkt": "12:00:00"
    },
    {
      "AfgivneStemmer": 1215,
      "AntalStemmeberretigedeVælgere": 3785,
      "Tidspunkt": "13:00:00"
    },
    {
      "AfgivneStemmer": 1408,
      "AntalStemmeberretigedeVælgere": 3785,
      "Tidspunkt": "14:00:00"
    },
    {
      "AfgivneStemmer": 1585,
      "AntalStemmeberretigedeVælgere": 3785,
      "Tidspunkt": "15:00:00"
    },
    {
      "AfgivneStemmer": 1815,
      "AntalStemmeberretigedeVælgere": 3785,
      "Tidspunkt": "16:00:00"
    },
    {
      "AfgivneStemmer": 2063,
      "AntalStemmeberretigedeVælgere": 3785,
      "Tidspunkt": "17:00:00"
    },
    {
      "AfgivneStemmer": 2288,
      "AntalStemmeberretigedeVælgere": 3785,
      "Tidspunkt": "18:00:00"
    },
    {
      "AfgivneStemmer": 2479,
      "AntalStemmeberretigedeVælgere": 3785,
      "Tidspunkt": "19:00:00"
    },
    {
      "AfgivneStemmer": 2636,
      "AntalStemmeberretigedeVælgere": 3785,
      "Tidspunkt": "20:00:00"
    }
  ]
}
