{
  "Afstemningsområde": "Klokkerholm",
  "AfstemningsområdeDagiId": "704006",
  "AfstemningsområdeNummer": 6,
  "FrigivelsesTidspunktUTC": "24-03-2026 17:12:02",
  "Kommune": "Brønderslev",
  "Kommunekode": 810,
  "Valgart": "Folketingsvalg",
  "Valgdag": "24-03-2026",
  "Valgdeltagelse": [
    {
      "AfgivneStemmer": 345,
      "AntalStemmeberretigedeVælgere": 1402,
      "Tidspunkt": "12:00:00"
    },
    {
      "AfgivneStemmer": 681,
      "AntalStemmeberretigedeVælgere": 1402,
      "Tidspunkt": "16:00:00"
    },
    {
      "AfgivneStemmer": 1021,
      "AntalStemmeberretigedeVælgere": 1402,
      "Tidspunkt": "18:00:00"
    }
  ]
}
