{
  "Afstemningsområde": "Læborg",
  "AfstemningsområdeDagiId": "703014",
  "AfstemningsområdeNummer": 15,
  "FrigivelsesTidspunktUTC": "24-03-2026 19:04:29",
  "Kommune": "Vejen",
  "Kommunekode": 575,
  "Valgart": "Folketingsvalg",
  "Valgdag": "24-03-2026",
  "Valgdeltagelse": [
    {
      "AfgivneStemmer": 77,
      "AntalStemmeberretigedeVælgere": 500,
      "Tidspunkt": "10:00:00"
    },
    {
      "AfgivneStemmer": 140,
      "AntalStemmeberretigedeVælgere": 500,
      "Tidspunkt": "13:00:00"
    },
    {
      "AfgivneStemmer": 230,
      "AntalStemmeberretigedeVælgere": 500,
      "Tidspunkt": "16:00:00"
    },
    {
      "AfgivneStemmer": 446,
      "AntalStemmeberretigedeVælgere": 500,
      "Tidspunkt": "20:00:00"
    }
  ]
}
