{
  "Afstemningsområde": "Ølholm",
  "AfstemningsområdeDagiId": "711316",
  "AfstemningsområdeNummer": 24,
  "FrigivelsesTidspunktUTC": "24-03-2026 13:10:57",
  "Kommune": "Hedensted",
  "Kommunekode": 766,
  "Valgart": "Folketingsvalg",
  "Valgdag": "24-03-2026",
  "Valgdeltagelse": [
    {
      "AfgivneStemmer": 62,
      "AntalStemmeberretigedeVælgere": 705,
      "Tidspunkt": "09:00:00"
    },
    {
      "AfgivneStemmer": 141,
      "AntalStemmeberretigedeVælgere": 705,
      "Tidspunkt": "12:00:00"
    }
  ]
}
