{
  "Afstemningsområde": "Brødeskov",
  "AfstemningsområdeDagiId": "701190",
  "AfstemningsområdeNummer": 3,
  "FrigivelsesTidspunktUTC": "24-03-2026 11:11:08",
  "Kommune": "Hillerød",
  "Kommunekode": 219,
  "Valgart": "Folketingsvalg",
  "Valgdag": "24-03-2026",
  "Valgdeltagelse": [
    {
      "AfgivneStemmer": 38,
      "AntalStemmeberretigedeVælgere": 629,
      "Tidspunkt": "08:00:00"
    },
    {
      "AfgivneStemmer": 87,
      "AntalStemmeberretigedeVælgere": 629,
      "Tidspunkt": "09:00:00"
    },
    {
      "AfgivneStemmer": 132,
      "AntalStemmeberretigedeVælgere": 629,
      "Tidspunkt": "10:00:00"
    },
    {
      "AfgivneStemmer": 169,
      "AntalStemmeberretigedeVælgere": 629,
      "Tidspunkt": "11:00:00"
    },
    {
      "AfgivneStemmer": 188,
      "AntalStemmeberretigedeVælgere": 629,
      "Tidspunkt": "12:00:00"
    }
  ]
}
