{
  "Afstemningsområde": "Errindlev",
  "AfstemningsområdeDagiId": "708426",
  "AfstemningsområdeNummer": 1,
  "FrigivelsesTidspunktUTC": "24-03-2026 19:06:35",
  "Kommune": "Lolland",
  "Kommunekode": 360,
  "Valgart": "Folketingsvalg",
  "Valgdag": "24-03-2026",
  "Valgdeltagelse": [
    {
      "AfgivneStemmer": 113,
      "AntalStemmeberretigedeVælgere": 528,
      "Tidspunkt": "10:00:00"
    },
    {
      "AfgivneStemmer": 203,
      "AntalStemmeberretigedeVælgere": 528,
      "Tidspunkt": "12:00:00"
    },
    {
      "AfgivneStemmer": 252,
      "AntalStemmeberretigedeVælgere": 528,
      "Tidspunkt": "14:00:00"
    },
    {
      "AfgivneStemmer": 319,
      "AntalStemmeberretigedeVælgere": 528,
      "Tidspunkt": "16:00:00"
    },
    {
      "AfgivneStemmer": 401,
      "AntalStemmeberretigedeVælgere": 528,
      "Tidspunkt": "18:00:00"
    },
    {
      "AfgivneStemmer": 444,
      "AntalStemmeberretigedeVælgere": 528,
      "Tidspunkt": "20:00:00"
    }
  ]
}
