{
  "Afstemningsområde": "Bindslev",
  "AfstemningsområdeDagiId": "708788",
  "AfstemningsområdeNummer": 7,
  "FrigivelsesTidspunktUTC": "24-03-2026 10:02:47",
  "Kommune": "Hjørring",
  "Kommunekode": 860,
  "Valgart": "Folketingsvalg",
  "Valgdag": "24-03-2026",
  "Valgdeltagelse": [
    {
      "AfgivneStemmer": 76,
      "AntalStemmeberretigedeVælgere": 1169,
      "Tidspunkt": "09:00:00"
    },
    {
      "AfgivneStemmer": 211,
      "AntalStemmeberretigedeVælgere": 1169,
      "Tidspunkt": "11:00:00"
    }
  ]
}
