{
  "Afstemningsområde": "Østmøn",
  "AfstemningsområdeDagiId": "712094",
  "AfstemningsområdeNummer": 9,
  "FrigivelsesTidspunktUTC": "24-03-2026 19:13:44",
  "Kommune": "Vordingborg",
  "Kommunekode": 390,
  "Valgart": "Folketingsvalg",
  "Valgdag": "24-03-2026",
  "Valgdeltagelse": [
    {
      "AfgivneStemmer": 185,
      "AntalStemmeberretigedeVælgere": 1070,
      "Tidspunkt": "10:00:00"
    },
    {
      "AfgivneStemmer": 348,
      "AntalStemmeberretigedeVælgere": 1070,
      "Tidspunkt": "12:00:00"
    },
    {
      "AfgivneStemmer": 484,
      "AntalStemmeberretigedeVælgere": 1070,
      "Tidspunkt": "14:00:00"
    },
    {
      "AfgivneStemmer": 610,
      "AntalStemmeberretigedeVælgere": 1070,
      "Tidspunkt": "16:00:00"
    },
    {
      "AfgivneStemmer": 794,
      "AntalStemmeberretigedeVælgere": 1070,
      "Tidspunkt": "18:00:00"
    },
    {
      "AfgivneStemmer": 871,
      "AntalStemmeberretigedeVælgere": 1070,
      "Tidspunkt": "20:00:00"
    }
  ]
}
