{
  "Afstemningsområde": "Glesborg",
  "AfstemningsområdeDagiId": "709072",
  "AfstemningsområdeNummer": 5,
  "FrigivelsesTidspunktUTC": "24-03-2026 11:02:56",
  "Kommune": "Norddjurs",
  "Kommunekode": 707,
  "Valgart": "Folketingsvalg",
  "Valgdag": "24-03-2026",
  "Valgdeltagelse": [
    {
      "AfgivneStemmer": 520,
      "AntalStemmeberretigedeVælgere": 2977,
      "Tidspunkt": "10:00:00"
    },
    {
      "AfgivneStemmer": 957,
      "AntalStemmeberretigedeVælgere": 2977,
      "Tidspunkt": "12:00:00"
    }
  ]
}
